rabbitmq2psql_as_json/__init__.py
rabbitmq2psql_as_json-1.0.4.data/scripts/rabbitmq2psql-as-json
rabbitmq2psql_as_json-1.0.4.dist-info/LICENSE
rabbitmq2psql_as_json-1.0.4.dist-info/METADATA
rabbitmq2psql_as_json-1.0.4.dist-info/WHEEL
rabbitmq2psql_as_json-1.0.4.dist-info/top_level.txt
rabbitmq2psql_as_json-1.0.4.dist-info/RECORD
