Metadata-Version: 2.1
Name: rabbitmq2psql-as-json
Version: 1.0.4
Summary: Asynchronous RabbitMQ consumer job library for PostgreSQL
Home-page: https://github.com/mantis-software-company/rabbitmq2psql-as-json
Author: Furkan Kalkan
Author-email: furkankalkan@mantis.com.tr
License: UNKNOWN
Platform: all
Classifier: License :: OSI Approved :: Apache Software License
Classifier: Topic :: Internet
Classifier: Topic :: Software Development
Classifier: Topic :: Software Development :: Libraries
Classifier: Topic :: Software Development :: Testing
Classifier: Intended Audience :: Developers
Classifier: Operating System :: MacOS
Classifier: Operating System :: POSIX
Classifier: Operating System :: Microsoft
Classifier: Programming Language :: Python
Classifier: Programming Language :: Python :: 3
Classifier: Programming Language :: Python :: 3.6
Classifier: Programming Language :: Python :: 3.7
Classifier: Programming Language :: Python :: 3.8
Requires-Python: >3.6.*, <4
Requires-Dist: aiopg
Requires-Dist: aio-pika
